{
  "files": {
    "posts_0": {
      "path": "posts/posts_0.json",
      "size": 1401,
      "lastUpdated": "2025-09-20T15:27:49.336Z",
      "count": 2
    },
    "comments_0": {
      "path": "comments/comments_0.json",
      "size": 2,
      "lastUpdated": "2025-09-20T07:31:15.520Z",
      "count": 0
    },
    "votes_0": {
      "path": "votes/votes_0.json",
      "size": 2,
      "lastUpdated": "2025-09-20T07:31:33.658Z",
      "count": 0
    },
    "comments_[object Object]": {
      "path": "comments/comments_[object Object].json",
      "size": 2,
      "lastUpdated": "2025-09-20T09:10:18.569Z"
    },
    "sites_0": {
      "path": "sites/sites_0.json",
      "size": 2038,
      "lastUpdated": "2025-09-20T15:27:39.130Z",
      "count": 5
    },
    "profiles_0": {
      "path": "profiles/profiles_0.json",
      "size": 532,
      "lastUpdated": "2025-09-20T15:33:42.978Z",
      "count": 1
    },
    "notification-settings_0": {
      "path": "notification-settings/notification-settings_0.json",
      "size": 88,
      "lastUpdated": "2025-09-20T15:33:48.398Z",
      "count": 1
    },
    "privacy-settings_0": {
      "path": "privacy-settings/privacy-settings_0.json",
      "size": 136,
      "lastUpdated": "2025-09-20T15:33:52.702Z",
      "count": 1
    }
  },
  "lastUpdated": "2025-09-20T15:33:52.703Z"
}